{
    "name": "Teensy Bare - MK64Fx512",
    "build": {
      "extra_flags": "",
      "cpu": "cortex-m4",
      "f_cpu": "120000000L",
      "mcu": "mk64fx512",
      "device": "MK64F12",
      "startup_file": "startup_MK64F12.S",
      "linker_file": "MK64FX512xxx12_flash.ld"
    },
    "debug": {
      "jlink_device": "MK64FX512xxx12",
      "svd_path": "MK64F12.svd"
    },
    "frameworks": [
      "azul"
    ],
    "upload": {
      "maximum_ram_size": 262144,
      "maximum_size": 524288,
      "protocol": "teensy-gui",
      "protocols": [
        "teensy-cli",
        "teensy-gui",
        "jlink"
      ]
    },
    "url": "https://www.HashDefineElectronics.com/",
    "vendor": "Freescale"
  }